{"version":1,"addons":{"formautofill@mozilla.org":{"id":"formautofill@mozilla.org","guid":"{9f2967c7-a43f-4b8d-9b08-47c895bbea11}","enabled":true,"installed":true,"modified":1755838442058,"type":"extension","scope":1,"foreignInstall":false,"isSyncable":false},"pictureinpicture@mozilla.org":{"id":"pictureinpicture@mozilla.org","guid":"{95e66f0e-38ad-44a8-9658-7ce1ac625cb7}","enabled":true,"installed":true,"modified":1755838442059,"type":"extension","scope":1,"foreignInstall":false,"isSyncable":false},"screenshots@mozilla.org":{"id":"screenshots@mozilla.org","guid":"{da194bc4-049e-4972-9c77-fe295a333a39}","enabled":false,"installed":true,"modified":1755838442059,"type":"extension","scope":1,"foreignInstall":false,"isSyncable":false},"webcompat-reporter@mozilla.org":{"id":"webcompat-reporter@mozilla.org","guid":"{b6840b9a-ee4d-4cb5-b66d-6bf43038a20c}","enabled":false,"installed":true,"modified":1755838442059,"type":"extension","scope":1,"foreignInstall":false,"isSyncable":false},"webcompat@mozilla.org":{"id":"webcompat@mozilla.org","guid":"{0069c50b-e87f-4954-bd9c-7bd871ba536d}","enabled":true,"installed":true,"modified":1755838442059,"type":"extension","scope":1,"foreignInstall":false,"isSyncable":false},"default-theme@mozilla.org":{"id":"default-theme@mozilla.org","guid":"{e2db6076-d6c9-4970-86c3-660a63ff96c8}","enabled":true,"installed":true,"modified":1755838442059,"type":"theme","scope":4,"foreignInstall":false,"isSyncable":false},"addons-search-detection@mozilla.com":{"id":"addons-search-detection@mozilla.com","guid":"{69a4295b-8fe2-4f55-b4bc-a81ef09d745f}","enabled":true,"installed":true,"modified":1755838442059,"type":"extension","scope":4,"foreignInstall":false,"isSyncable":false},"firefox-compact-light@mozilla.org":{"id":"firefox-compact-light@mozilla.org","guid":"{056fde4c-d301-474c-ab9e-93e2b6aa9cf6}","enabled":false,"installed":true,"modified":1755838442059,"type":"theme","scope":4,"foreignInstall":false,"isSyncable":false},"firefox-compact-dark@mozilla.org":{"id":"firefox-compact-dark@mozilla.org","guid":"{754a7b18-10eb-4291-84e2-9f5fa3ce848b}","enabled":false,"installed":true,"modified":1755838442059,"type":"theme","scope":4,"foreignInstall":false,"isSyncable":false},"firefox-alpenglow@mozilla.org":{"id":"firefox-alpenglow@mozilla.org","guid":"{c672d10b-28ae-4a5b-a120-62b8c2d13dec}","enabled":false,"installed":true,"modified":1755838442060,"type":"theme","scope":4,"foreignInstall":false,"isSyncable":false},"hotfix-intermediate-2018@mozilla.com":{"id":"hotfix-intermediate-2018@mozilla.com","guid":"{f45bf25d-5b2a-4e9f-958a-8289d673dd0e}","enabled":true,"installed":true,"modified":1755838442060,"type":"extension","scope":1,"foreignInstall":false,"isSyncable":false},"langpack-en-US@firefox.mozilla.org":{"id":"langpack-en-US@firefox.mozilla.org","guid":"{420ac8b6-b5b3-45a6-a689-f0666f78830a}","enabled":true,"installed":true,"modified":1755838442060,"type":"locale","scope":1,"foreignInstall":false,"isSyncable":true},"gmp-gmpopenh264":{"id":"gmp-gmpopenh264","enabled":true,"installed":true,"modified":1755838442060,"type":"plugin","scope":4,"foreignInstall":false}},"changes":[[1755838442058,1,"formautofill@mozilla.org"],[1755838442059,1,"pictureinpicture@mozilla.org"],[1755838442059,1,"screenshots@mozilla.org"],[1755838442059,1,"webcompat-reporter@mozilla.org"],[1755838442059,1,"webcompat@mozilla.org"],[1755838442059,1,"default-theme@mozilla.org"],[1755838442059,1,"addons-search-detection@mozilla.com"],[1755838442059,1,"firefox-compact-light@mozilla.org"],[1755838442059,1,"firefox-compact-dark@mozilla.org"],[1755838442060,1,"firefox-alpenglow@mozilla.org"],[1755838442060,1,"hotfix-intermediate-2018@mozilla.com"],[1755838442060,1,"langpack-en-US@firefox.mozilla.org"],[1755838442060,1,"gmp-gmpopenh264"]]}